[
    {
        "accountAlias": "FzFzmYTiFzmYTisR",
        "asset": "FDUSD",
        "balance": "0.00000000",
        "crossWalletBalance": "0.00000000",
        "crossUnPnl": "0.00000000",
        "availableBalance": "0.00000000",
        "maxWithdrawAmount": "0.00000000",
        "marginAvailable": true,
        "updateTime": 0
    },
    {
        "accountAlias": "FzFzmYTiFzmYTisR",
        "asset": "BTC",
        "balance": "0.00000000",
        "crossWalletBalance": "0.00000000",
        "crossUnPnl": "0.00000000",
        "availableBalance": "0.00000000",
        "maxWithdrawAmount": "0.00000000",
        "marginAvailable": true,
        "updateTime": 0
    },
    {
        "accountAlias": "FzFzmYTiFzmYTisR",
        "asset": "BNB",
        "balance": "0.00000017",
        "crossWalletBalance": "0.00000017",
        "crossUnPnl": "0.00000000",
        "availableBalance": "0.00000017",
        "maxWithdrawAmount": "0.00000017",
        "marginAvailable": true,
        "updateTime": 1725655880412
    },
    {
        "accountAlias": "FzFzmYTiFzmYTisR",
        "asset": "ETH",
        "balance": "0.00000000",
        "crossWalletBalance": "0.00000000",
        "crossUnPnl": "0.00000000",
        "availableBalance": "0.00000000",
        "maxWithdrawAmount": "0.00000000",
        "marginAvailable": true,
        "updateTime": 0
    },
    {
        "accountAlias": "FzFzmYTiFzmYTisR",
        "asset": "USDT",
        "balance": "129.69910320",
        "crossWalletBalance": "129.69910320",
        "crossUnPnl": "0.35131776",
        "availableBalance": "85.82781055",
        "maxWithdrawAmount": "85.82781055",
        "marginAvailable": true,
        "updateTime": 1729449300720
    },
    {
        "accountAlias": "FzFzmYTiFzmYTisR",
        "asset": "USDC",
        "balance": "0.00000000",
        "crossWalletBalance": "0.00000000",
        "crossUnPnl": "0.00000000",
        "availableBalance": "0.00000000",
        "maxWithdrawAmount": "0.00000000",
        "marginAvailable": true,
        "updateTime": 0
    }
]